cdtlog/__init__.py
cdtlog/cdtlog.py
cdtlog/common.py
cmpdisktree/__init__.py
cmpdisktree/comparer.py
cmpdisktree/debug.py
cmpdisktree/exclusions.py
cmpdisktree/main.py
cmpdisktree/utils.py
cmpdisktree-0.2.1.dist-info/METADATA
cmpdisktree-0.2.1.dist-info/WHEEL
cmpdisktree-0.2.1.dist-info/entry_points.txt
cmpdisktree-0.2.1.dist-info/top_level.txt
cmpdisktree-0.2.1.dist-info/RECORD
