Metadata-Version: 2.1
Name: cmpdisktree
Version: 0.2.1
Summary: Compare Directories as macOS Disk Structures
Home-page: https://github.com/halloleo/cmpdisktree
Author: halloleo
Author-email: cmpdisktree@halloleo.hailmail.net
License: License :: OSI Approved :: GNU General Public License v3 (GPLv3)
Keywords: system,man,help
Platform: UNKNOWN
Classifier: Programming Language :: Python
Classifier: Programming Language :: Python :: 3
Classifier: Programming Language :: Python :: Implementation :: CPython
Classifier: Development Status :: 4 - Beta
Classifier: Environment :: Console
Classifier: Intended Audience :: Developers
Classifier: Intended Audience :: System Administrators
Classifier: Natural Language :: English
Classifier: Operating System :: MacOS :: MacOS X
Classifier: Operating System :: POSIX
Classifier: Operating System :: Unix
Classifier: Topic :: System :: Archiving :: Backup
Classifier: Topic :: System :: Filesystems
Classifier: Topic :: System :: Systems Administration
Classifier: Topic :: Utilities
Requires-Python: >=3.6
Requires-Dist: click
Requires-Dist: tqdm
